Metadata-Version: 2.1
Name: distributions-from-mercy
Version: 0.1
Summary: Gaussian distributions
Home-page: UNKNOWN
License: UNKNOWN
Platform: UNKNOWN
License-File: licence.txt
